{
    "crea_cilindro": [
        {
            "raggio": 6.0,
            "spostamento_z": 1.0,
            "spostamento_z2": 0.75,
            "visione_boss": false,
            "pos_finale": {
                "x": 0.0,
                "y": 0.0,
                "z": 194.71902465820313
            }
        }
    ],
    "crea_blocco": [
        {
            "mesh": {
                "instanceID": -876284
            },
            "mesh_dissolve": {
                "instanceID": 0
            },
            "mesh_renderer": {
                "instanceID": 0
            },
            "struttura_procedurale": "3230002313400212232",
            "struttura_procedurale_dz": "5534264656326345526",
            "punto_impatto": {
                "x": 0.0,
                "y": 0.0,
                "z": 0.0
            },
            "forza_impatto": 0.0,
            "tipo": 100,
            "attivo": 0,
            "arrivo": 0,
            "disattiva_coll": 0,
            "distruzione_oggetto": 0,
            "valore_dissolve": 0.0,
            "altezza": 0.0,
            "rad": 0.1745329350233078,
            "pos": 23.491477966308595,
            "rotazione": 0.0
        },
        {
            "mesh": {
                "instanceID": -876296
            },
            "mesh_dissolve": {
                "instanceID": 0
            },
            "mesh_renderer": {
                "instanceID": 0
            },
            "struttura_procedurale": "",
            "struttura_procedurale_dz": "",
            "punto_impatto": {
                "x": 0.0,
                "y": 0.0,
                "z": 0.0
            },
            "forza_impatto": 0.0,
            "tipo": 3,
            "attivo": 0,
            "arrivo": 0,
            "disattiva_coll": 0,
            "distruzione_oggetto": 0,
            "valore_dissolve": 0.0,
            "altezza": 0.0,
            "rad": -0.07026658207178116,
            "pos": 39.41740036010742,
            "rotazione": 0.0
        },
        {
            "mesh": {
                "instanceID": -876310
            },
            "mesh_dissolve": {
                "instanceID": 0
            },
            "mesh_renderer": {
                "instanceID": 0
            },
            "struttura_procedurale": "",
            "struttura_procedurale_dz": "",
            "punto_impatto": {
                "x": 0.0,
                "y": 0.0,
                "z": 0.0
            },
            "forza_impatto": 0.0,
            "tipo": 3,
            "attivo": 0,
            "arrivo": 0,
            "disattiva_coll": 0,
            "distruzione_oggetto": 0,
            "valore_dissolve": 0.0,
            "altezza": 0.0,
            "rad": 1.5981289148330689,
            "pos": 51.534576416015628,
            "rotazione": 0.0
        },
        {
            "mesh": {
                "instanceID": -876324
            },
            "mesh_dissolve": {
                "instanceID": 0
            },
            "mesh_renderer": {
                "instanceID": 0
            },
            "struttura_procedurale": "",
            "struttura_procedurale_dz": "",
            "punto_impatto": {
                "x": 0.0,
                "y": 0.0,
                "z": 0.0
            },
            "forza_impatto": 0.0,
            "tipo": 3,
            "attivo": 0,
            "arrivo": 0,
            "disattiva_coll": 0,
            "distruzione_oggetto": 0,
            "valore_dissolve": 0.0,
            "altezza": 0.0,
            "rad": 3.084455728530884,
            "pos": 35.03960037231445,
            "rotazione": 0.0
        },
        {
            "mesh": {
                "instanceID": -876338
            },
            "mesh_dissolve": {
                "instanceID": 0
            },
            "mesh_renderer": {
                "instanceID": 0
            },
            "struttura_procedurale": "",
            "struttura_procedurale_dz": "",
            "punto_impatto": {
                "x": 0.0,
                "y": 0.0,
                "z": 0.0
            },
            "forza_impatto": 0.0,
            "tipo": 3,
            "attivo": 0,
            "arrivo": 0,
            "disattiva_coll": 0,
            "distruzione_oggetto": 0,
            "valore_dissolve": 0.0,
            "altezza": 0.0,
            "rad": 4.729319095611572,
            "pos": 40.05836486816406,
            "rotazione": 0.0
        },
        {
            "mesh": {
                "instanceID": -876352
            },
            "mesh_dissolve": {
                "instanceID": 0
            },
            "mesh_renderer": {
                "instanceID": 0
            },
            "struttura_procedurale": "4331111110042001014",
            "struttura_procedurale_dz": "2355523252644626533",
            "punto_impatto": {
                "x": 0.0,
                "y": 0.0,
                "z": 0.0
            },
            "forza_impatto": 0.0,
            "tipo": 100,
            "attivo": 0,
            "arrivo": 0,
            "disattiva_coll": 0,
            "distruzione_oggetto": 0,
            "valore_dissolve": 0.0,
            "altezza": 0.0,
            "rad": 0.1745329350233078,
            "pos": 43.95583724975586,
            "rotazione": 0.0
        },
        {
            "mesh": {
                "instanceID": -876364
            },
            "mesh_dissolve": {
                "instanceID": 0
            },
            "mesh_renderer": {
                "instanceID": 0
            },
            "struttura_procedurale": "",
            "struttura_procedurale_dz": "",
            "punto_impatto": {
                "x": 0.0,
                "y": 0.0,
                "z": 0.0
            },
            "forza_impatto": 0.0,
            "tipo": 4,
            "attivo": 0,
            "arrivo": 0,
            "disattiva_coll": 0,
            "distruzione_oggetto": 0,
            "valore_dissolve": 0.0,
            "altezza": 0.0,
            "rad": 0.017052028328180314,
            "pos": 52.04876708984375,
            "rotazione": 0.0
        },
        {
            "mesh": {
                "instanceID": -876378
            },
            "mesh_dissolve": {
                "instanceID": 0
            },
            "mesh_renderer": {
                "instanceID": 0
            },
            "struttura_procedurale": "",
            "struttura_procedurale_dz": "",
            "punto_impatto": {
                "x": 0.0,
                "y": 0.0,
                "z": 0.0
            },
            "forza_impatto": 0.0,
            "tipo": 3,
            "attivo": 0,
            "arrivo": 0,
            "disattiva_coll": 0,
            "distruzione_oggetto": 0,
            "valore_dissolve": 0.0,
            "altezza": 0.0,
            "rad": 1.4566740989685059,
            "pos": 55.79769515991211,
            "rotazione": 0.0
        },
        {
            "mesh": {
                "instanceID": -876392
            },
            "mesh_dissolve": {
                "instanceID": 0
            },
            "mesh_renderer": {
                "instanceID": 0
            },
            "struttura_procedurale": "",
            "struttura_procedurale_dz": "",
            "punto_impatto": {
                "x": 0.0,
                "y": 0.0,
                "z": 0.0
            },
            "forza_impatto": 0.0,
            "tipo": 3,
            "attivo": 0,
            "arrivo": 0,
            "disattiva_coll": 0,
            "distruzione_oggetto": 0,
            "valore_dissolve": 0.0,
            "altezza": 0.0,
            "rad": 3.223618507385254,
            "pos": 39.1301155090332,
            "rotazione": 0.0
        },
        {
            "mesh": {
                "instanceID": -876406
            },
            "mesh_dissolve": {
                "instanceID": 0
            },
            "mesh_renderer": {
                "instanceID": 0
            },
            "struttura_procedurale": "",
            "struttura_procedurale_dz": "",
            "punto_impatto": {
                "x": 0.0,
                "y": 0.0,
                "z": 0.0
            },
            "forza_impatto": 0.0,
            "tipo": 4,
            "attivo": 0,
            "arrivo": 0,
            "disattiva_coll": 0,
            "distruzione_oggetto": 0,
            "valore_dissolve": 0.0,
            "altezza": 0.0,
            "rad": 4.599307060241699,
            "pos": 60.96723175048828,
            "rotazione": 0.0
        },
        {
            "mesh": {
                "instanceID": -876420
            },
            "mesh_dissolve": {
                "instanceID": 0
            },
            "mesh_renderer": {
                "instanceID": 0
            },
            "struttura_procedurale": "2220023233200031114",
            "struttura_procedurale_dz": "5245436444555335342",
            "punto_impatto": {
                "x": 0.0,
                "y": 0.0,
                "z": 0.0
            },
            "forza_impatto": 0.0,
            "tipo": 100,
            "attivo": 0,
            "arrivo": 0,
            "disattiva_coll": 0,
            "distruzione_oggetto": 0,
            "valore_dissolve": 0.0,
            "altezza": 0.0,
            "rad": 0.1745329350233078,
            "pos": 45.09492492675781,
            "rotazione": 0.0
        },
        {
            "mesh": {
                "instanceID": -876432
            },
            "mesh_dissolve": {
                "instanceID": 0
            },
            "mesh_renderer": {
                "instanceID": 0
            },
            "struttura_procedurale": "",
            "struttura_procedurale_dz": "",
            "punto_impatto": {
                "x": 0.0,
                "y": 0.0,
                "z": 0.0
            },
            "forza_impatto": 0.0,
            "tipo": 3,
            "attivo": 0,
            "arrivo": 0,
            "disattiva_coll": 0,
            "distruzione_oggetto": 0,
            "valore_dissolve": 0.0,
            "altezza": 0.0,
            "rad": -0.0065974220633506779,
            "pos": 62.26398468017578,
            "rotazione": 0.0
        },
        {
            "mesh": {
                "instanceID": -876446
            },
            "mesh_dissolve": {
                "instanceID": 0
            },
            "mesh_renderer": {
                "instanceID": 0
            },
            "struttura_procedurale": "",
            "struttura_procedurale_dz": "",
            "punto_impatto": {
                "x": 0.0,
                "y": 0.0,
                "z": 0.0
            },
            "forza_impatto": 0.0,
            "tipo": 4,
            "attivo": 0,
            "arrivo": 0,
            "disattiva_coll": 0,
            "distruzione_oggetto": 0,
            "valore_dissolve": 0.0,
            "altezza": 0.0,
            "rad": 1.5545247793197632,
            "pos": 64.0938949584961,
            "rotazione": 0.0
        },
        {
            "mesh": {
                "instanceID": -876460
            },
            "mesh_dissolve": {
                "instanceID": 0
            },
            "mesh_renderer": {
                "instanceID": 0
            },
            "struttura_procedurale": "",
            "struttura_procedurale_dz": "",
            "punto_impatto": {
                "x": 0.0,
                "y": 0.0,
                "z": 0.0
            },
            "forza_impatto": 0.0,
            "tipo": 4,
            "attivo": 0,
            "arrivo": 0,
            "disattiva_coll": 0,
            "distruzione_oggetto": 0,
            "valore_dissolve": 0.0,
            "altezza": 0.0,
            "rad": 3.24601149559021,
            "pos": 64.36589813232422,
            "rotazione": 0.0
        },
        {
            "mesh": {
                "instanceID": -876474
            },
            "mesh_dissolve": {
                "instanceID": 0
            },
            "mesh_renderer": {
                "instanceID": 0
            },
            "struttura_procedurale": "0043140038983132141",
            "struttura_procedurale_dz": "2225462563223635566",
            "punto_impatto": {
                "x": 0.0,
                "y": 0.0,
                "z": 0.0
            },
            "forza_impatto": 0.0,
            "tipo": 100,
            "attivo": 0,
            "arrivo": 0,
            "disattiva_coll": 0,
            "distruzione_oggetto": 0,
            "valore_dissolve": 0.0,
            "altezza": 0.0,
            "rad": 0.1745329350233078,
            "pos": 66.08264923095703,
            "rotazione": 0.0
        },
        {
            "mesh": {
                "instanceID": -876486
            },
            "mesh_dissolve": {
                "instanceID": 0
            },
            "mesh_renderer": {
                "instanceID": 0
            },
            "struttura_procedurale": "",
            "struttura_procedurale_dz": "",
            "punto_impatto": {
                "x": 0.0,
                "y": 0.0,
                "z": 0.0
            },
            "forza_impatto": 0.0,
            "tipo": 4,
            "attivo": 0,
            "arrivo": 0,
            "disattiva_coll": 0,
            "distruzione_oggetto": 0,
            "valore_dissolve": 0.0,
            "altezza": 0.0,
            "rad": -0.08789697289466858,
            "pos": 58.63652420043945,
            "rotazione": 0.0
        },
        {
            "mesh": {
                "instanceID": -876500
            },
            "mesh_dissolve": {
                "instanceID": 0
            },
            "mesh_renderer": {
                "instanceID": 0
            },
            "struttura_procedurale": "",
            "struttura_procedurale_dz": "",
            "punto_impatto": {
                "x": 0.0,
                "y": 0.0,
                "z": 0.0
            },
            "forza_impatto": 0.0,
            "tipo": 3,
            "attivo": 0,
            "arrivo": 0,
            "disattiva_coll": 0,
            "distruzione_oggetto": 0,
            "valore_dissolve": 0.0,
            "altezza": 0.0,
            "rad": 4.725327491760254,
            "pos": 65.0694808959961,
            "rotazione": 0.0
        },
        {
            "mesh": {
                "instanceID": -876514
            },
            "mesh_dissolve": {
                "instanceID": 0
            },
            "mesh_renderer": {
                "instanceID": 0
            },
            "struttura_procedurale": "1412121200433003411",
            "struttura_procedurale_dz": "5646545356636254643",
            "punto_impatto": {
                "x": 0.0,
                "y": 0.0,
                "z": 0.0
            },
            "forza_impatto": 0.0,
            "tipo": 100,
            "attivo": 0,
            "arrivo": 0,
            "disattiva_coll": 0,
            "distruzione_oggetto": 0,
            "valore_dissolve": 0.0,
            "altezza": 0.0,
            "rad": 0.1745329350233078,
            "pos": 74.69393157958985,
            "rotazione": 0.0
        },
        {
            "mesh": {
                "instanceID": -876526
            },
            "mesh_dissolve": {
                "instanceID": 0
            },
            "mesh_renderer": {
                "instanceID": 0
            },
            "struttura_procedurale": "",
            "struttura_procedurale_dz": "",
            "punto_impatto": {
                "x": 0.0,
                "y": 0.0,
                "z": 0.0
            },
            "forza_impatto": 0.0,
            "tipo": 4,
            "attivo": 0,
            "arrivo": 0,
            "disattiva_coll": 0,
            "distruzione_oggetto": 0,
            "valore_dissolve": 0.0,
            "altezza": 0.0,
            "rad": 0.004171155393123627,
            "pos": 84.50252532958985,
            "rotazione": 0.0
        },
        {
            "mesh": {
                "instanceID": -876540
            },
            "mesh_dissolve": {
                "instanceID": 0
            },
            "mesh_renderer": {
                "instanceID": 0
            },
            "struttura_procedurale": "",
            "struttura_procedurale_dz": "",
            "punto_impatto": {
                "x": 0.0,
                "y": 0.0,
                "z": 0.0
            },
            "forza_impatto": 0.0,
            "tipo": 3,
            "attivo": 0,
            "arrivo": 0,
            "disattiva_coll": 0,
            "distruzione_oggetto": 0,
            "valore_dissolve": 0.0,
            "altezza": 0.0,
            "rad": 3.0465519428253176,
            "pos": 88.80293273925781,
            "rotazione": 0.0
        },
        {
            "mesh": {
                "instanceID": -876554
            },
            "mesh_dissolve": {
                "instanceID": 0
            },
            "mesh_renderer": {
                "instanceID": 0
            },
            "struttura_procedurale": "",
            "struttura_procedurale_dz": "",
            "punto_impatto": {
                "x": 0.0,
                "y": 0.0,
                "z": 0.0
            },
            "forza_impatto": 0.0,
            "tipo": 4,
            "attivo": 0,
            "arrivo": 0,
            "disattiva_coll": 0,
            "distruzione_oggetto": 0,
            "valore_dissolve": 0.0,
            "altezza": 0.0,
            "rad": 4.648343086242676,
            "pos": 74.4998779296875,
            "rotazione": 0.0
        },
        {
            "mesh": {
                "instanceID": -876568
            },
            "mesh_dissolve": {
                "instanceID": 0
            },
            "mesh_renderer": {
                "instanceID": 0
            },
            "struttura_procedurale": "4122334242111100300",
            "struttura_procedurale_dz": "5533342632465264433",
            "punto_impatto": {
                "x": 0.0,
                "y": 0.0,
                "z": 0.0
            },
            "forza_impatto": 0.0,
            "tipo": 100,
            "attivo": 0,
            "arrivo": 0,
            "disattiva_coll": 0,
            "distruzione_oggetto": 0,
            "valore_dissolve": 0.0,
            "altezza": 0.0,
            "rad": 0.1745329350233078,
            "pos": 95.33938598632813,
            "rotazione": 0.0
        },
        {
            "mesh": {
                "instanceID": -876580
            },
            "mesh_dissolve": {
                "instanceID": 0
            },
            "mesh_renderer": {
                "instanceID": 0
            },
            "struttura_procedurale": "",
            "struttura_procedurale_dz": "",
            "punto_impatto": {
                "x": 0.0,
                "y": 0.0,
                "z": 0.0
            },
            "forza_impatto": 0.0,
            "tipo": 3,
            "attivo": 0,
            "arrivo": 0,
            "disattiva_coll": 0,
            "distruzione_oggetto": 0,
            "valore_dissolve": 0.0,
            "altezza": 0.0,
            "rad": 0.0854790061712265,
            "pos": 93.92355346679688,
            "rotazione": 0.0
        },
        {
            "mesh": {
                "instanceID": -876594
            },
            "mesh_dissolve": {
                "instanceID": 0
            },
            "mesh_renderer": {
                "instanceID": 0
            },
            "struttura_procedurale": "",
            "struttura_procedurale_dz": "",
            "punto_impatto": {
                "x": 0.0,
                "y": 0.0,
                "z": 0.0
            },
            "forza_impatto": 0.0,
            "tipo": 3,
            "attivo": 0,
            "arrivo": 0,
            "disattiva_coll": 0,
            "distruzione_oggetto": 0,
            "valore_dissolve": 0.0,
            "altezza": 0.0,
            "rad": 1.539990782737732,
            "pos": 79.2166976928711,
            "rotazione": 0.0
        },
        {
            "mesh": {
                "instanceID": -876608
            },
            "mesh_dissolve": {
                "instanceID": 0
            },
            "mesh_renderer": {
                "instanceID": 0
            },
            "struttura_procedurale": "",
            "struttura_procedurale_dz": "",
            "punto_impatto": {
                "x": 0.0,
                "y": 0.0,
                "z": 0.0
            },
            "forza_impatto": 0.0,
            "tipo": 4,
            "attivo": 0,
            "arrivo": 0,
            "disattiva_coll": 0,
            "distruzione_oggetto": 0,
            "valore_dissolve": 0.0,
            "altezza": 0.0,
            "rad": 3.0696206092834474,
            "pos": 95.06969451904297,
            "rotazione": 0.0
        },
        {
            "mesh": {
                "instanceID": -876622
            },
            "mesh_dissolve": {
                "instanceID": 0
            },
            "mesh_renderer": {
                "instanceID": 0
            },
            "struttura_procedurale": "2243321233898100300",
            "struttura_procedurale_dz": "2666555543424255244",
            "punto_impatto": {
                "x": 0.0,
                "y": 0.0,
                "z": 0.0
            },
            "forza_impatto": 0.0,
            "tipo": 100,
            "attivo": 0,
            "arrivo": 0,
            "disattiva_coll": 0,
            "distruzione_oggetto": 0,
            "valore_dissolve": 0.0,
            "altezza": 0.0,
            "rad": 0.1745329350233078,
            "pos": 84.9962158203125,
            "rotazione": 0.0
        },
        {
            "mesh": {
                "instanceID": -876634
            },
            "mesh_dissolve": {
                "instanceID": 0
            },
            "mesh_renderer": {
                "instanceID": 0
            },
            "struttura_procedurale": "",
            "struttura_procedurale_dz": "",
            "punto_impatto": {
                "x": 0.0,
                "y": 0.0,
                "z": 0.0
            },
            "forza_impatto": 0.0,
            "tipo": 4,
            "attivo": 0,
            "arrivo": 0,
            "disattiva_coll": 0,
            "distruzione_oggetto": 0,
            "valore_dissolve": 0.0,
            "altezza": 0.0,
            "rad": 1.5397390127182007,
            "pos": 92.87248229980469,
            "rotazione": 0.0
        },
        {
            "mesh": {
                "instanceID": -876648
            },
            "mesh_dissolve": {
                "instanceID": 0
            },
            "mesh_renderer": {
                "instanceID": 0
            },
            "struttura_procedurale": "",
            "struttura_procedurale_dz": "",
            "punto_impatto": {
                "x": 0.0,
                "y": 0.0,
                "z": 0.0
            },
            "forza_impatto": 0.0,
            "tipo": 3,
            "attivo": 0,
            "arrivo": 0,
            "disattiva_coll": 0,
            "distruzione_oggetto": 0,
            "valore_dissolve": 0.0,
            "altezza": 0.0,
            "rad": 3.0713276863098146,
            "pos": 98.68655395507813,
            "rotazione": 0.0
        },
        {
            "mesh": {
                "instanceID": -876662
            },
            "mesh_dissolve": {
                "instanceID": 0
            },
            "mesh_renderer": {
                "instanceID": 0
            },
            "struttura_procedurale": "4120041241100389814",
            "struttura_procedurale_dz": "5553232462332222635",
            "punto_impatto": {
                "x": 0.0,
                "y": 0.0,
                "z": 0.0
            },
            "forza_impatto": 0.0,
            "tipo": 100,
            "attivo": 0,
            "arrivo": 0,
            "disattiva_coll": 0,
            "distruzione_oggetto": 0,
            "valore_dissolve": 0.0,
            "altezza": 0.0,
            "rad": 0.1745329350233078,
            "pos": 114.08121490478516,
            "rotazione": 0.0
        },
        {
            "mesh": {
                "instanceID": -876674
            },
            "mesh_dissolve": {
                "instanceID": 0
            },
            "mesh_renderer": {
                "instanceID": 0
            },
            "struttura_procedurale": "",
            "struttura_procedurale_dz": "",
            "punto_impatto": {
                "x": 0.0,
                "y": 0.0,
                "z": 0.0
            },
            "forza_impatto": 0.0,
            "tipo": 3,
            "attivo": 0,
            "arrivo": 0,
            "disattiva_coll": 0,
            "distruzione_oggetto": 0,
            "valore_dissolve": 0.0,
            "altezza": 0.0,
            "rad": -0.11827351897954941,
            "pos": 108.98790740966797,
            "rotazione": 0.0
        },
        {
            "mesh": {
                "instanceID": -876688
            },
            "mesh_dissolve": {
                "instanceID": 0
            },
            "mesh_renderer": {
                "instanceID": 0
            },
            "struttura_procedurale": "",
            "struttura_procedurale_dz": "",
            "punto_impatto": {
                "x": 0.0,
                "y": 0.0,
                "z": 0.0
            },
            "forza_impatto": 0.0,
            "tipo": 3,
            "attivo": 0,
            "arrivo": 0,
            "disattiva_coll": 0,
            "distruzione_oggetto": 0,
            "valore_dissolve": 0.0,
            "altezza": 0.0,
            "rad": 1.6561205387115479,
            "pos": 111.06159973144531,
            "rotazione": 0.0
        },
        {
            "mesh": {
                "instanceID": -876702
            },
            "mesh_dissolve": {
                "instanceID": 0
            },
            "mesh_renderer": {
                "instanceID": 0
            },
            "struttura_procedurale": "",
            "struttura_procedurale_dz": "",
            "punto_impatto": {
                "x": 0.0,
                "y": 0.0,
                "z": 0.0
            },
            "forza_impatto": 0.0,
            "tipo": 3,
            "attivo": 0,
            "arrivo": 0,
            "disattiva_coll": 0,
            "distruzione_oggetto": 0,
            "valore_dissolve": 0.0,
            "altezza": 0.0,
            "rad": 3.1993637084960939,
            "pos": 108.13987731933594,
            "rotazione": 0.0
        },
        {
            "mesh": {
                "instanceID": -876716
            },
            "mesh_dissolve": {
                "instanceID": 0
            },
            "mesh_renderer": {
                "instanceID": 0
            },
            "struttura_procedurale": "1300122121241002343",
            "struttura_procedurale_dz": "5323325332632544346",
            "punto_impatto": {
                "x": 0.0,
                "y": 0.0,
                "z": 0.0
            },
            "forza_impatto": 0.0,
            "tipo": 100,
            "attivo": 0,
            "arrivo": 0,
            "disattiva_coll": 0,
            "distruzione_oggetto": 0,
            "valore_dissolve": 0.0,
            "altezza": 0.0,
            "rad": 0.1745329350233078,
            "pos": 115.40045166015625,
            "rotazione": 0.0
        },
        {
            "mesh": {
                "instanceID": -876728
            },
            "mesh_dissolve": {
                "instanceID": 0
            },
            "mesh_renderer": {
                "instanceID": 0
            },
            "struttura_procedurale": "",
            "struttura_procedurale_dz": "",
            "punto_impatto": {
                "x": 0.0,
                "y": 0.0,
                "z": 0.0
            },
            "forza_impatto": 0.0,
            "tipo": 3,
            "attivo": 0,
            "arrivo": 0,
            "disattiva_coll": 0,
            "distruzione_oggetto": 0,
            "valore_dissolve": 0.0,
            "altezza": 0.0,
            "rad": -0.014543019235134125,
            "pos": 126.4910888671875,
            "rotazione": 0.0
        },
        {
            "mesh": {
                "instanceID": -876742
            },
            "mesh_dissolve": {
                "instanceID": 0
            },
            "mesh_renderer": {
                "instanceID": 0
            },
            "struttura_procedurale": "",
            "struttura_procedurale_dz": "",
            "punto_impatto": {
                "x": 0.0,
                "y": 0.0,
                "z": 0.0
            },
            "forza_impatto": 0.0,
            "tipo": 4,
            "attivo": 0,
            "arrivo": 0,
            "disattiva_coll": 0,
            "distruzione_oggetto": 0,
            "valore_dissolve": 0.0,
            "altezza": 0.0,
            "rad": 1.573907732963562,
            "pos": 126.31155395507813,
            "rotazione": 0.0
        },
        {
            "mesh": {
                "instanceID": -876756
            },
            "mesh_dissolve": {
                "instanceID": 0
            },
            "mesh_renderer": {
                "instanceID": 0
            },
            "struttura_procedurale": "",
            "struttura_procedurale_dz": "",
            "punto_impatto": {
                "x": 0.0,
                "y": 0.0,
                "z": 0.0
            },
            "forza_impatto": 0.0,
            "tipo": 4,
            "attivo": 0,
            "arrivo": 0,
            "disattiva_coll": 0,
            "distruzione_oggetto": 0,
            "valore_dissolve": 0.0,
            "altezza": 0.0,
            "rad": 4.631040573120117,
            "pos": 131.68350219726563,
            "rotazione": 0.0
        },
        {
            "mesh": {
                "instanceID": -876770
            },
            "mesh_dissolve": {
                "instanceID": 0
            },
            "mesh_renderer": {
                "instanceID": 0
            },
            "struttura_procedurale": "1898332134410010234",
            "struttura_procedurale_dz": "5235232262633654563",
            "punto_impatto": {
                "x": 0.0,
                "y": 0.0,
                "z": 0.0
            },
            "forza_impatto": 0.0,
            "tipo": 100,
            "attivo": 0,
            "arrivo": 0,
            "disattiva_coll": 0,
            "distruzione_oggetto": 0,
            "valore_dissolve": 0.0,
            "altezza": 0.0,
            "rad": 0.1745329350233078,
            "pos": 114.53629302978516,
            "rotazione": 0.0
        },
        {
            "mesh": {
                "instanceID": -876782
            },
            "mesh_dissolve": {
                "instanceID": 0
            },
            "mesh_renderer": {
                "instanceID": 0
            },
            "struttura_procedurale": "",
            "struttura_procedurale_dz": "",
            "punto_impatto": {
                "x": 0.0,
                "y": 0.0,
                "z": 0.0
            },
            "forza_impatto": 0.0,
            "tipo": 3,
            "attivo": 0,
            "arrivo": 0,
            "disattiva_coll": 0,
            "distruzione_oggetto": 0,
            "valore_dissolve": 0.0,
            "altezza": 0.0,
            "rad": -0.10827378183603287,
            "pos": 139.9564208984375,
            "rotazione": 0.0
        },
        {
            "mesh": {
                "instanceID": -876796
            },
            "mesh_dissolve": {
                "instanceID": 0
            },
            "mesh_renderer": {
                "instanceID": 0
            },
            "struttura_procedurale": "",
            "struttura_procedurale_dz": "",
            "punto_impatto": {
                "x": 0.0,
                "y": 0.0,
                "z": 0.0
            },
            "forza_impatto": 0.0,
            "tipo": 3,
            "attivo": 0,
            "arrivo": 0,
            "disattiva_coll": 0,
            "distruzione_oggetto": 0,
            "valore_dissolve": 0.0,
            "altezza": 0.0,
            "rad": 1.6244691610336304,
            "pos": 118.42146301269531,
            "rotazione": 0.0
        },
        {
            "mesh": {
                "instanceID": -876810
            },
            "mesh_dissolve": {
                "instanceID": 0
            },
            "mesh_renderer": {
                "instanceID": 0
            },
            "struttura_procedurale": "1212131200132343114",
            "struttura_procedurale_dz": "5346444342664425635",
            "punto_impatto": {
                "x": 0.0,
                "y": 0.0,
                "z": 0.0
            },
            "forza_impatto": 0.0,
            "tipo": 100,
            "attivo": 0,
            "arrivo": 0,
            "disattiva_coll": 0,
            "distruzione_oggetto": 0,
            "valore_dissolve": 0.0,
            "altezza": 0.0,
            "rad": 0.1745329350233078,
            "pos": 132.79998779296876,
            "rotazione": 0.0
        },
        {
            "mesh": {
                "instanceID": -876822
            },
            "mesh_dissolve": {
                "instanceID": 0
            },
            "mesh_renderer": {
                "instanceID": 0
            },
            "struttura_procedurale": "",
            "struttura_procedurale_dz": "",
            "punto_impatto": {
                "x": 0.0,
                "y": 0.0,
                "z": 0.0
            },
            "forza_impatto": 0.0,
            "tipo": 4,
            "attivo": 0,
            "arrivo": 0,
            "disattiva_coll": 0,
            "distruzione_oggetto": 0,
            "valore_dissolve": 0.0,
            "altezza": 0.0,
            "rad": 1.6866264343261719,
            "pos": 150.7826385498047,
            "rotazione": 0.0
        },
        {
            "mesh": {
                "instanceID": -876836
            },
            "mesh_dissolve": {
                "instanceID": 0
            },
            "mesh_renderer": {
                "instanceID": 0
            },
            "struttura_procedurale": "",
            "struttura_procedurale_dz": "",
            "punto_impatto": {
                "x": 0.0,
                "y": 0.0,
                "z": 0.0
            },
            "forza_impatto": 0.0,
            "tipo": 3,
            "attivo": 0,
            "arrivo": 0,
            "disattiva_coll": 0,
            "distruzione_oggetto": 0,
            "valore_dissolve": 0.0,
            "altezza": 0.0,
            "rad": 3.1293208599090578,
            "pos": 136.5500030517578,
            "rotazione": 0.0
        },
        {
            "mesh": {
                "instanceID": -876850
            },
            "mesh_dissolve": {
                "instanceID": 0
            },
            "mesh_renderer": {
                "instanceID": 0
            },
            "struttura_procedurale": "3333300011210022231",
            "struttura_procedurale_dz": "2256632242256343245",
            "punto_impatto": {
                "x": 0.0,
                "y": 0.0,
                "z": 0.0
            },
            "forza_impatto": 0.0,
            "tipo": 100,
            "attivo": 0,
            "arrivo": 0,
            "disattiva_coll": 0,
            "distruzione_oggetto": 0,
            "valore_dissolve": 0.0,
            "altezza": 0.0,
            "rad": 0.1745329350233078,
            "pos": 133.9412078857422,
            "rotazione": 0.0
        },
        {
            "mesh": {
                "instanceID": -876862
            },
            "mesh_dissolve": {
                "instanceID": 0
            },
            "mesh_renderer": {
                "instanceID": 0
            },
            "struttura_procedurale": "",
            "struttura_procedurale_dz": "",
            "punto_impatto": {
                "x": 0.0,
                "y": 0.0,
                "z": 0.0
            },
            "forza_impatto": 0.0,
            "tipo": 3,
            "attivo": 0,
            "arrivo": 0,
            "disattiva_coll": 0,
            "distruzione_oggetto": 0,
            "valore_dissolve": 0.0,
            "altezza": 0.0,
            "rad": 0.07623275369405747,
            "pos": 144.2174072265625,
            "rotazione": 0.0
        },
        {
            "mesh": {
                "instanceID": -876876
            },
            "mesh_dissolve": {
                "instanceID": 0
            },
            "mesh_renderer": {
                "instanceID": 0
            },
            "struttura_procedurale": "",
            "struttura_procedurale_dz": "",
            "punto_impatto": {
                "x": 0.0,
                "y": 0.0,
                "z": 0.0
            },
            "forza_impatto": 0.0,
            "tipo": 3,
            "attivo": 0,
            "arrivo": 0,
            "disattiva_coll": 0,
            "distruzione_oggetto": 0,
            "valore_dissolve": 0.0,
            "altezza": 0.0,
            "rad": 1.5247687101364136,
            "pos": 157.89744567871095,
            "rotazione": 0.0
        },
        {
            "mesh": {
                "instanceID": -876890
            },
            "mesh_dissolve": {
                "instanceID": 0
            },
            "mesh_renderer": {
                "instanceID": 0
            },
            "struttura_procedurale": "1112221230020013134",
            "struttura_procedurale_dz": "6632244364643435542",
            "punto_impatto": {
                "x": 0.0,
                "y": 0.0,
                "z": 0.0
            },
            "forza_impatto": 0.0,
            "tipo": 100,
            "attivo": 0,
            "arrivo": 0,
            "disattiva_coll": 0,
            "distruzione_oggetto": 0,
            "valore_dissolve": 0.0,
            "altezza": 0.0,
            "rad": 0.1745329350233078,
            "pos": 160.5077667236328,
            "rotazione": 0.0
        },
        {
            "mesh": {
                "instanceID": -876902
            },
            "mesh_dissolve": {
                "instanceID": 0
            },
            "mesh_renderer": {
                "instanceID": 0
            },
            "struttura_procedurale": "",
            "struttura_procedurale_dz": "",
            "punto_impatto": {
                "x": 0.0,
                "y": 0.0,
                "z": 0.0
            },
            "forza_impatto": 0.0,
            "tipo": 3,
            "attivo": 0,
            "arrivo": 0,
            "disattiva_coll": 0,
            "distruzione_oggetto": 0,
            "valore_dissolve": 0.0,
            "altezza": 0.0,
            "rad": 0.012515474110841751,
            "pos": 162.7980194091797,
            "rotazione": 0.0
        },
        {
            "mesh": {
                "instanceID": -876916
            },
            "mesh_dissolve": {
                "instanceID": 0
            },
            "mesh_renderer": {
                "instanceID": 0
            },
            "struttura_procedurale": "",
            "struttura_procedurale_dz": "",
            "punto_impatto": {
                "x": 0.0,
                "y": 0.0,
                "z": 0.0
            },
            "forza_impatto": 0.0,
            "tipo": 4,
            "attivo": 0,
            "arrivo": 0,
            "disattiva_coll": 0,
            "distruzione_oggetto": 0,
            "valore_dissolve": 0.0,
            "altezza": 0.0,
            "rad": 3.170389175415039,
            "pos": 156.27430725097657,
            "rotazione": 0.0
        },
        {
            "mesh": {
                "instanceID": -876930
            },
            "mesh_dissolve": {
                "instanceID": 0
            },
            "mesh_renderer": {
                "instanceID": 0
            },
            "struttura_procedurale": "",
            "struttura_procedurale_dz": "",
            "punto_impatto": {
                "x": 0.0,
                "y": 0.0,
                "z": 0.0
            },
            "forza_impatto": 0.0,
            "tipo": 3,
            "attivo": 0,
            "arrivo": 0,
            "disattiva_coll": 0,
            "distruzione_oggetto": 0,
            "valore_dissolve": 0.0,
            "altezza": 0.0,
            "rad": 4.628981590270996,
            "pos": 165.71412658691407,
            "rotazione": 0.0
        },
        {
            "mesh": {
                "instanceID": -876944
            },
            "mesh_dissolve": {
                "instanceID": 0
            },
            "mesh_renderer": {
                "instanceID": 0
            },
            "struttura_procedurale": "3310031242898311123",
            "struttura_procedurale_dz": "5245644252346465622",
            "punto_impatto": {
                "x": 0.0,
                "y": 0.0,
                "z": 0.0
            },
            "forza_impatto": 0.0,
            "tipo": 100,
            "attivo": 0,
            "arrivo": 0,
            "disattiva_coll": 0,
            "distruzione_oggetto": 0,
            "valore_dissolve": 0.0,
            "altezza": 0.0,
            "rad": 0.1745329350233078,
            "pos": 160.08612060546876,
            "rotazione": 0.0
        },
        {
            "mesh": {
                "instanceID": -876956
            },
            "mesh_dissolve": {
                "instanceID": 0
            },
            "mesh_renderer": {
                "instanceID": 0
            },
            "struttura_procedurale": "",
            "struttura_procedurale_dz": "",
            "punto_impatto": {
                "x": 0.0,
                "y": 0.0,
                "z": 0.0
            },
            "forza_impatto": 0.0,
            "tipo": 3,
            "attivo": 0,
            "arrivo": 0,
            "disattiva_coll": 0,
            "distruzione_oggetto": 0,
            "valore_dissolve": 0.0,
            "altezza": 0.0,
            "rad": 1.557669997215271,
            "pos": 174.93064880371095,
            "rotazione": 0.0
        },
        {
            "mesh": {
                "instanceID": -876970
            },
            "mesh_dissolve": {
                "instanceID": 0
            },
            "mesh_renderer": {
                "instanceID": 0
            },
            "struttura_procedurale": "",
            "struttura_procedurale_dz": "",
            "punto_impatto": {
                "x": 0.0,
                "y": 0.0,
                "z": 0.0
            },
            "forza_impatto": 0.0,
            "tipo": 4,
            "attivo": 0,
            "arrivo": 0,
            "disattiva_coll": 0,
            "distruzione_oggetto": 0,
            "valore_dissolve": 0.0,
            "altezza": 0.0,
            "rad": 3.1062705516815187,
            "pos": 165.72821044921876,
            "rotazione": 0.0
        },
        {
            "mesh": {
                "instanceID": -876984
            },
            "mesh_dissolve": {
                "instanceID": 0
            },
            "mesh_renderer": {
                "instanceID": 0
            },
            "struttura_procedurale": "",
            "struttura_procedurale_dz": "",
            "punto_impatto": {
                "x": 0.0,
                "y": 0.0,
                "z": 0.0
            },
            "forza_impatto": 0.0,
            "tipo": 4,
            "attivo": 0,
            "arrivo": 0,
            "disattiva_coll": 0,
            "distruzione_oggetto": 0,
            "valore_dissolve": 0.0,
            "altezza": 0.0,
            "rad": 4.64089298248291,
            "pos": 158.34042358398438,
            "rotazione": 0.0
        },
        {
            "mesh": {
                "instanceID": -876998
            },
            "mesh_dissolve": {
                "instanceID": 0
            },
            "mesh_renderer": {
                "instanceID": 0
            },
            "struttura_procedurale": "1221434234400033220",
            "struttura_procedurale_dz": "4264642242353343644",
            "punto_impatto": {
                "x": 0.0,
                "y": 0.0,
                "z": 0.0
            },
            "forza_impatto": 0.0,
            "tipo": 100,
            "attivo": 0,
            "arrivo": 0,
            "disattiva_coll": 0,
            "distruzione_oggetto": 0,
            "valore_dissolve": 0.0,
            "altezza": 0.0,
            "rad": 0.1745329350233078,
            "pos": 174.71902465820313,
            "rotazione": 0.0
        },
        {
            "mesh": {
                "instanceID": -877010
            },
            "mesh_dissolve": {
                "instanceID": 0
            },
            "mesh_renderer": {
                "instanceID": 0
            },
            "struttura_procedurale": "",
            "struttura_procedurale_dz": "",
            "punto_impatto": {
                "x": 0.0,
                "y": 0.0,
                "z": 0.0
            },
            "forza_impatto": 0.0,
            "tipo": 3,
            "attivo": 0,
            "arrivo": 0,
            "disattiva_coll": 0,
            "distruzione_oggetto": 0,
            "valore_dissolve": 0.0,
            "altezza": 0.0,
            "rad": -0.08647916465997696,
            "pos": 188.58816528320313,
            "rotazione": 0.0
        },
        {
            "mesh": {
                "instanceID": -877024
            },
            "mesh_dissolve": {
                "instanceID": 0
            },
            "mesh_renderer": {
                "instanceID": 0
            },
            "struttura_procedurale": "",
            "struttura_procedurale_dz": "",
            "punto_impatto": {
                "x": 0.0,
                "y": 0.0,
                "z": 0.0
            },
            "forza_impatto": 0.0,
            "tipo": 4,
            "attivo": 0,
            "arrivo": 0,
            "disattiva_coll": 0,
            "distruzione_oggetto": 0,
            "valore_dissolve": 0.0,
            "altezza": 0.0,
            "rad": 1.5279405117034913,
            "pos": 186.9066925048828,
            "rotazione": 0.0
        },
        {
            "mesh": {
                "instanceID": -877038
            },
            "mesh_dissolve": {
                "instanceID": 0
            },
            "mesh_renderer": {
                "instanceID": 0
            },
            "struttura_procedurale": "",
            "struttura_procedurale_dz": "",
            "punto_impatto": {
                "x": 0.0,
                "y": 0.0,
                "z": 0.0
            },
            "forza_impatto": 0.0,
            "tipo": 3,
            "attivo": 0,
            "arrivo": 0,
            "disattiva_coll": 0,
            "distruzione_oggetto": 0,
            "valore_dissolve": 0.0,
            "altezza": 0.0,
            "rad": 3.0333433151245119,
            "pos": 180.50259399414063,
            "rotazione": 0.0
        },
        {
            "mesh": {
                "instanceID": -877052
            },
            "mesh_dissolve": {
                "instanceID": 0
            },
            "mesh_renderer": {
                "instanceID": 0
            },
            "struttura_procedurale": "",
            "struttura_procedurale_dz": "",
            "punto_impatto": {
                "x": 0.0,
                "y": 0.0,
                "z": 0.0
            },
            "forza_impatto": 0.0,
            "tipo": 4,
            "attivo": 0,
            "arrivo": 0,
            "disattiva_coll": 0,
            "distruzione_oggetto": 0,
            "valore_dissolve": 0.0,
            "altezza": 0.0,
            "rad": 4.816058158874512,
            "pos": 191.88055419921876,
            "rotazione": 0.0
        }
    ],
    "crea_bonus": [],
    "crea_malus": [],
    "crea_moneta": [],
    "crea_gemma": []
}